submissions/phase_4/imm.v
// The immediate generator is responsible for decoding the 32-bit
// sign-extended immediate from the incoming instruction word. It is a purely
// combinational block that is expected to be embedded in the instruction
// decoder.
module imm (
    // Input instruction word. This is used to extract the relevant immediate
    // bits and assemble them into the final immediate.
    input  wire [31:0] i_inst,
    // Instruction format, determined by the instruction decoder based on the
    // opcode. This is one-hot encoded according to the following format:
    // [0] R-type
    // [1] I-type
    // [2] S-type
    // [3] B-type
    // [4] U-type
    // [5] J-type
    // Because the R-type format does not have an immediate, the output
    // immediate can be treated as a don't-care under this case.
    input  wire [ 5:0] i_format,
    // Output 32-bit immediate, sign-extended from the immediate bitstring.
    output reg  [31:0] o_immediate
);

    // Extract raw bit-fields according to RISC-V RV32I specification
    wire [31:0] imm_i = {{20{i_inst[31]}}, i_inst[31:20]};
    wire [31:0] imm_s = {{20{i_inst[31]}}, i_inst[31:25], i_inst[11:7]};
    wire [31:0] imm_b = {{20{i_inst[31]}}, i_inst[7], i_inst[30:25], i_inst[11:8], 1'b0};
    wire [31:0] imm_u = {i_inst[31:12], 12'b0};
    wire [31:0] imm_j = {{12{i_inst[31]}}, i_inst[19:12], i_inst[20], i_inst[30:21], 1'b0};

    // Combinational logic using case statement based on one-hot format encoding
    always @(*) begin
        case (i_format)
            6'b000010: o_immediate = imm_i; // I-type [1]
            6'b000100: o_immediate = imm_s; // S-type [2]
            6'b001000: o_immediate = imm_b; // B-type [3]
            6'b010000: o_immediate = imm_u; // U-type [4]
            6'b100000: o_immediate = imm_j; // J-type [5]
            default:   o_immediate = 32'b0; // R-type [0] or illegal format default
        endcase
    end

endmodule

submissions/phase_2/decoder.v
`default_nettype none

module decoder (
    // Input instruction word.
    input  wire [31:0] i_inst,
    // Asserted if the instruction was decoded as a legal instruction. It is
    // important that the decoder not accept any illegal instruction
    // encodings as this could lead to undefined behavior in the processor
    // which is a safety hazard.
    output wire        o_legal,
    // Indicates that the instruction is an ebreak and should halt execution.
    output wire        o_halt,
    // First source register address.
    // For instructions that do not use a source register, this is effectively
    // a don't care because reading unused registers does not have any side
    // effects (and we don't care about power usage, really).
    output wire [ 4:0] o_rs1,
    // Second source register address.
    // Similarly to o_rs1, this is a don't care for instructions that do not
    // read a (second) source register.
    output wire [ 4:0] o_rs2,
    // Destination register address.
    // For instructions that do not write to a register, this must be set to
    // x0 so the value is discarded. This avoids the need for a separate write
    // enable since discard behavior must be present anyway.
    output wire [ 4:0] o_rd,
    // 32-bit immediate value, decoded from the instruction word. For R-type
    // instructions that do not use an immediate, this is a don't care.
    output wire [31:0] o_immediate,
    // Selects whether the first operand for the ALU is fed by the first
    // register source (rs1) or the current pc.
    // When asserted, the second operand is the immediate.
    output wire        o_op1_sel,
    // Selects whether the second operand for the ALU is fed by the second
    // register source (rs2) or the immediate.
    // When asserted, the second operand is the immediate.
    output wire        o_op2_sel,
    // Major opsel for the ALU. See ALU documentation for the encoding.
    output wire [ 2:0] o_alu_opsel,
    // Minor opsel flags for the ALU. See ALU documentation for the encoding.
    output wire        o_alu_sub,
    output wire        o_alu_unsigned,
    output wire        o_alu_arith,
    // If asserted, the instruction is a branch instruction and the PC should
    // be updated to the target address if the branch condition is met.
    output wire        o_branch,
    // If asserted, the instruction is a jump instruction and the PC should
    // be updated to the target address unconditionally.
    output wire        o_jump,
    // When asserted, the branch comparator checks for equality. When not
    // asserted, it checks for less than [unsigned].
    output wire        o_branch_equal,
    // When asserted, the branch comparator treats the less than comparison
    // operands as unsigned. This is only used when `!o_branch_equal`.
    output wire        o_branch_unsigned,
    // When asserted, the branch condition is inverted.
    // Equality -> inequality, less than -> greater than or equal.
    output wire        o_branch_invert,
    // When asserted, the instruction will load from memory.
    output wire        o_dmem_ren,
    // When asserted, the instruction will store to memory.
    output wire        o_dmem_wen,
    // This 2-bit mask selects which LSBs of the memory address should be
    // checked for alignment. This is because byte and half-word accesses need
    // only be 1-byte and 2-byte aligned, respectively.
    output wire [ 1:0] o_dmem_align,
    // These 3 bits select the size of the memory access.
    // They are effectively one-hot encoded.
    output wire        o_dmem_memb,
    output wire        o_dmem_memh,
    output wire        o_dmem_memw,
    // If asserted, the (byte or half-word) memory access is unsigned and the
    // load should be zero-extended to 32 bits instead of sign-extended.
    output wire        o_dmem_memu,
    // Selects the data to write to the destination register, one-hot.
    // [0] = ALU result
    // [1] = immediate
    // [2] = PC + 4
    // [3] = memory
    output wire [ 3:0] o_rd_sel,
    // If asserted, the PC jumps to the target address calculated by the ALU
    // rather than directly to the PC + immediate. This is used for JALR.
    output wire        o_pc_sel
);

   // Opcode Decoding
   wire is_arr     = (i_inst[6:0] == 7'b0110011);
   wire is_arr_imm = (i_inst[6:0] == 7'b0010011);
   wire is_load    = (i_inst[6:0] == 7'b0000011);
   wire is_lui     = (i_inst[6:0] == 7'b0110111);
   wire is_auipc   = (i_inst[6:0] == 7'b0010111);
   wire is_store   = (i_inst[6:0] == 7'b0100011);
   wire is_branch  = (i_inst[6:0] == 7'b1100011);
   wire is_jal     = (i_inst[6:0] == 7'b1101111);
   wire is_jalr    = (i_inst[6:0] == 7'b1100111);
   wire is_system  = (i_inst[6:0] == 7'b1110011);

   wire [5:0] format = (is_arr | is_system)             ? 6'b000001 :
                       (is_arr_imm | is_load | is_jalr) ? 6'b000010 :
                       (is_store)                       ? 6'b000100 :
                       (is_branch)                      ? 6'b001000 :
                       (is_lui | is_auipc)              ? 6'b010000 :
                       (is_jal)                         ? 6'b100000 : 6'b000000;

   assign o_halt  = (i_inst == 32'h00100073);
   assign o_legal = is_arr | is_arr_imm | is_load | is_lui | is_auipc | is_store | is_branch | is_jal | is_jalr | o_halt;
   

   // rs1, rs2, and rd are always in the same place (unless they don't exist, in which case don't care)
   assign o_rd  = i_inst[11: 7];
   assign o_rs1 = i_inst[19:15];
   assign o_rs2 = i_inst[24:20];
   
   imm imm (.i_inst      (i_inst),
            .i_format    (format),
            .o_immediate (o_immediate)
            );

   assign o_op1_sel      = is_auipc | is_jal;
   assign o_op2_sel      = ~(is_arr | is_branch);
   assign o_alu_opsel    = (is_arr | is_arr_imm | is_branch) ? i_inst[14:12] : 3'b000; // funct3 if we're arithmetic or branch, or addition for other ops
   assign o_alu_sub      = is_arr & i_inst[   30]; // second digit of funct7 (if we're doing arithmetic)
   assign o_alu_unsigned = i_inst[   30]; // ditto (imm goes around this bit)
   assign o_alu_arith    = i_inst[   30]; // ditto

   assign o_branch = is_branch;
   assign o_jump   = is_jal | is_jalr;
    
   assign o_branch_equal    = ~i_inst[14];
   assign o_branch_unsigned = i_inst[13];
   assign o_branch_invert   = i_inst[12];
    
   assign o_dmem_ren   = is_load;
   assign o_dmem_wen   = is_store;
   assign o_dmem_memb  = ~(i_inst[13] | i_inst[12]);
   assign o_dmem_memh  = i_inst[12];
   assign o_dmem_memw  = i_inst[13];
   assign o_dmem_align = {o_dmem_memh, ~o_dmem_memw};
   assign o_dmem_memu  = i_inst[14];
   
    assign o_rd_sel = (is_arr | is_arr_imm | is_auipc) ? 4'b0001 :
                     (is_lui)                         ? 4'b0010 :
                     (is_jal | is_jalr)               ? 4'b0100 :
                     (is_load)                        ? 4'b1000 : 4'b0000;
   
   assign o_pc_sel = is_jalr;

endmodule

`default_nettype wire

testbenches/phase_2/decoder_tb.v
`timescale 1ns / 1ps
`default_nettype none

module decoder_tb;

    reg  [31:0] inst;

    wire        legal;
    wire        halt;
    wire [4:0]  rs1;
    wire [4:0]  rs2;
    wire [4:0]  rd;
    wire [31:0] immediate;
    wire        op1_sel;
    wire        op2_sel;
    wire [2:0]  alu_opsel;
    wire        alu_sub;
    wire        alu_unsigned;
    wire        alu_arith;
    wire        branch;
    wire        jump;
    wire        branch_equal;
    wire        branch_unsigned;
    wire        branch_invert;
    wire        dmem_ren;
    wire        dmem_wen;
    wire [1:0]  dmem_align;
    wire        dmem_memb;
    wire        dmem_memh;
    wire        dmem_memw;
    wire        dmem_memu;
    wire [3:0]  rd_sel;
    wire        pc_sel;

    integer passed;
    integer failed;

    decoder dut (
        .i_inst            (inst),
        .o_legal           (legal),
        .o_halt            (halt),
        .o_rs1             (rs1),
        .o_rs2             (rs2),
        .o_rd              (rd),
        .o_immediate       (immediate),
        .o_op1_sel         (op1_sel),
        .o_op2_sel         (op2_sel),
        .o_alu_opsel       (alu_opsel),
        .o_alu_sub         (alu_sub),
        .o_alu_unsigned    (alu_unsigned),
        .o_alu_arith       (alu_arith),
        .o_branch          (branch),
        .o_jump            (jump),
        .o_branch_equal    (branch_equal),
        .o_branch_unsigned (branch_unsigned),
        .o_branch_invert   (branch_invert),
        .o_dmem_ren        (dmem_ren),
        .o_dmem_wen        (dmem_wen),
        .o_dmem_align      (dmem_align),
        .o_dmem_memb       (dmem_memb),
        .o_dmem_memh       (dmem_memh),
        .o_dmem_memw       (dmem_memw),
        .o_dmem_memu       (dmem_memu),
        .o_rd_sel          (rd_sel),
        .o_pc_sel          (pc_sel)
    );

    task check;
        input [511:0] label;
        input         e_legal;
        input         e_halt;
        input [4:0]   e_rs1;
        input [4:0]   e_rs2;
        input [4:0]   e_rd;
        input [31:0]  e_imm;
        input         e_op1_sel;
        input         e_op2_sel;
        input [2:0]   e_alu_opsel;
        input         e_alu_sub;
        input         e_branch;
        input         e_jump;
        input         e_ren;
        input         e_wen;
        input [3:0]   e_rd_sel;
        input         e_pc_sel;
        begin
            #1;
            if (legal === e_legal &&
                halt === e_halt &&
                rs1 === e_rs1 &&
                rs2 === e_rs2 &&
                rd === e_rd &&
                immediate === e_imm &&
                op1_sel === e_op1_sel &&
                op2_sel === e_op2_sel &&
                alu_opsel === e_alu_opsel &&
                alu_sub === e_alu_sub &&
                branch === e_branch &&
                jump === e_jump &&
                dmem_ren === e_ren &&
                dmem_wen === e_wen &&
                rd_sel === e_rd_sel &&
                pc_sel === e_pc_sel) begin
                passed = passed + 1;
                $display("[PASS] %0s", label);
            end else begin
                failed = failed + 1;
                $display("[FAIL] %0s", label);
                $display("       inst=%h", inst);
                $display("       legal=%b/%b halt=%b/%b rs1=%0d/%0d rs2=%0d/%0d rd=%0d/%0d",
                         legal,e_legal,halt,e_halt,rs1,e_rs1,rs2,e_rs2,rd,e_rd);
                $display("       imm=%h/%h op1_sel=%b/%b op2_sel=%b/%b alu=%b/%b sub=%b/%b",
                         immediate,e_imm,op1_sel,e_op1_sel,op2_sel,e_op2_sel,
                         alu_opsel,e_alu_opsel,alu_sub,e_alu_sub);
                $display("       branch=%b/%b jump=%b/%b ren=%b/%b wen=%b/%b rd_sel=%b/%b pc_sel=%b/%b",
                         branch,e_branch,jump,e_jump,dmem_ren,e_ren,dmem_wen,e_wen,
                         rd_sel,e_rd_sel,pc_sel,e_pc_sel);
            end
        end
    endtask

    initial begin
        $dumpfile("decoder_tb.vcd");
        $dumpvars(0, decoder_tb);

        passed = 0;
        failed = 0;

        $display("========== DECODER testbench ==========");

        // add x5,x6,x7
        inst = 32'h007302b3;
        check("R-type ADD", 1,0,6,7,5,0,0,0,3'b000,0,0,0,0,0,4'b0001,0);

        // sub x5,x6,x7
        inst = 32'h407302b3;
        check("R-type SUB", 1,0,6,7,5,0,0,0,3'b000,1,0,0,0,0,4'b0001,0);

        // xori x5,x5,-1
        inst = 32'hfff2c293;
        check("I-type XORI", 1,0,5,0,5,32'hffff_ffff,0,1,3'b100,0,0,0,0,0,4'b0001,0);

        // lui x5,0x12345
        inst = 32'h123452b7;
        check("LUI", 1,0,0,0,5,32'h1234_5000,0,1,3'b000,0,0,0,0,0,4'b0010,0);

        // auipc x5,0x12345
        inst = 32'h12345297;
        check("AUIPC", 1,0,0,0,5,32'h1234_5000,1,1,3'b000,0,0,0,0,0,4'b0001,0);

        // lw x5,8(x6)
        inst = 32'h00832283;
        check("LW", 1,0,6,0,5,32'd8,0,1,3'b000,0,0,0,1,0,4'b1000,0);

        // sw x5,8(x6)
        inst = 32'h00532423;
        check("SW", 1,0,6,5,0,32'd8,0,1,3'b000,0,0,0,0,1,4'b0000,0);

        // beq x5,x6,+16
        inst = 32'h00628863;
        check("BEQ", 1,0,5,6,0,32'd16,0,0,3'b000,0,1,0,0,0,4'b0000,0);

        // jal x5,+16
        inst = 32'h010002ef;
        check("JAL", 1,0,0,0,5,32'd16,1,1,3'b000,0,0,1,0,0,4'b0100,0);

        // jalr x5,12(x6)
        inst = 32'h00c302e7;
        check("JALR", 1,0,6,0,5,32'd12,0,1,3'b000,0,0,1,0,0,4'b0100,1);

        // ebreak
        inst = 32'h00100073;
        check("EBREAK", 0,1,0,0,0,0,0,1,3'b000,0,0,0,0,0,4'b0000,0);

        $display("=======================================");
        $display("%0d passed, %0d failed", passed, failed);
        if (failed == 0) $display("ALL TESTS PASSED");
        else             $display("TEST FAILED");
        $finish;
    end

endmodule

`default_nettype wire

tests/phase_2/decoder_tb.vcd
$date
	Thu Sep 10 16:44:51 2026
$end
$version
	Icarus Verilog
$end
$timescale
	1ps
$end
$scope module decoder_tb $end
$var wire 5 ! rs2 [4:0] $end
$var wire 5 " rs1 [4:0] $end
$var wire 4 # rd_sel [3:0] $end
$var wire 5 $ rd [4:0] $end
$var wire 1 % pc_sel $end
$var wire 1 & op2_sel $end
$var wire 1 ' op1_sel $end
$var wire 1 ( legal $end
$var wire 1 ) jump $end
$var wire 32 * immediate [31:0] $end
$var wire 1 + halt $end
$var wire 1 , dmem_wen $end
$var wire 1 - dmem_ren $end
$var wire 1 . dmem_memw $end
$var wire 1 / dmem_memu $end
$var wire 1 0 dmem_memh $end
$var wire 1 1 dmem_memb $end
$var wire 2 2 dmem_align [1:0] $end
$var wire 1 3 branch_unsigned $end
$var wire 1 4 branch_invert $end
$var wire 1 5 branch_equal $end
$var wire 1 6 branch $end
$var wire 1 7 alu_unsigned $end
$var wire 1 8 alu_sub $end
$var wire 3 9 alu_opsel [2:0] $end
$var wire 1 : alu_arith $end
$var reg 32 ; inst [31:0] $end
$var integer 32 < failed [31:0] $end
$var integer 32 = passed [31:0] $end
$scope module dut $end
$var wire 32 > i_inst [31:0] $end
$var wire 1 8 o_alu_sub $end
$var wire 1 6 o_branch $end
$var wire 1 5 o_branch_equal $end
$var wire 1 1 o_dmem_memb $end
$var wire 1 - o_dmem_ren $end
$var wire 1 , o_dmem_wen $end
$var wire 1 ) o_jump $end
$var wire 1 ( o_legal $end
$var wire 1 ' o_op1_sel $end
$var wire 1 & o_op2_sel $end
$var wire 1 % o_pc_sel $end
$var wire 5 ? o_rs2 [4:0] $end
$var wire 5 @ o_rs1 [4:0] $end
$var wire 4 A o_rd_sel [3:0] $end
$var wire 5 B o_rd [4:0] $end
$var wire 32 C o_immediate [31:0] $end
$var wire 1 + o_halt $end
$var wire 1 . o_dmem_memw $end
$var wire 1 / o_dmem_memu $end
$var wire 1 0 o_dmem_memh $end
$var wire 2 D o_dmem_align [1:0] $end
$var wire 1 3 o_branch_unsigned $end
$var wire 1 4 o_branch_invert $end
$var wire 1 7 o_alu_unsigned $end
$var wire 3 E o_alu_opsel [2:0] $end
$var wire 1 : o_alu_arith $end
$var wire 1 F is_system $end
$var wire 1 G is_store $end
$var wire 1 H is_lui $end
$var wire 1 I is_load $end
$var wire 1 J is_jalr $end
$var wire 1 K is_jal $end
$var wire 1 L is_branch $end
$var wire 1 M is_auipc $end
$var wire 1 N is_arr_imm $end
$var wire 1 O is_arr $end
$var wire 6 P format [5:0] $end
$scope module imm $end
$var wire 6 Q i_format [5:0] $end
$var wire 32 R i_inst [31:0] $end
$var wire 32 S imm_u [31:0] $end
$var wire 32 T imm_s [31:0] $end
$var wire 32 U imm_j [31:0] $end
$var wire 32 V imm_i [31:0] $end
$var wire 32 W imm_b [31:0] $end
$var reg 32 X o_immediate [31:0] $end
$upscope $end
$upscope $end
$scope task check $end
$var reg 3 Y e_alu_opsel [2:0] $end
$var reg 1 Z e_alu_sub $end
$var reg 1 [ e_branch $end
$var reg 1 \ e_halt $end
$var reg 32 ] e_imm [31:0] $end
$var reg 1 ^ e_jump $end
$var reg 1 _ e_legal $end
$var reg 1 ` e_op1_sel $end
$var reg 1 a e_op2_sel $end
$var reg 1 b e_pc_sel $end
$var reg 5 c e_rd [4:0] $end
$var reg 4 d e_rd_sel [3:0] $end
$var reg 1 e e_ren $end
$var reg 5 f e_rs1 [4:0] $end
$var reg 5 g e_rs2 [4:0] $end
$var reg 1 h e_wen $end
$var reg 512 i label [511:0] $end
$upscope $end
$upscope $end
$enddefinitions $end
$comment Show the parameter values. $end
$dumpall
$end
#0
$dumpvars
b1010010001011010111010001111001011100000110010100100000010000010100010001000100 i
0h
b111 g
b110 f
0e
b1 d
b101 c
0b
0a
0`
1_
0^
b0 ]
0\
0[
0Z
b0 Y
b0 X
b100000000100 W
b111 V
b110000100000000110 U
b101 T
b11100110000000000000000 S
b11100110000001010110011 R
b1 Q
b1 P
1O
0N
0M
0L
0K
0J
0I
0H
0G
0F
b0 E
b1 D
b0 C
b101 B
b1 A
b110 @
b111 ?
b11100110000001010110011 >
b0 =
b0 <
b11100110000001010110011 ;
0:
b0 9
08
07
06
15
04
03
b1 2
11
00
0/
0.
0-
0,
0+
b0 *
0)
1(
0'
0&
0%
b101 $
b1 #
b110 "
b111 !
$end
#1000
18
17
1:
b10000000111 V
b10000000101 T
b110000000100 W
b1000000011100110000000000000000 S
b110000110000000110 U
1Z
b1010010001011010111010001111001011100000110010100100000010100110101010101000010 i
b1000000011100110000001010110011 ;
b1000000011100110000001010110011 >
b1000000011100110000001010110011 R
b1 =
#2000
b11111111111111111111111111111111 *
b11111111111111111111111111111111 C
b11111111111111111111111111111111 X
1&
b10 P
b10 Q
08
b100 9
b100 E
05
0O
1N
b101 "
b101 @
b11111 !
b11111 ?
1/
b11111111111111111111111111111111 V
b11111111111111111111111111100101 T
b11111111111111111111111111100100 W
b11111111111100101100000000000000 S
b11111111111100101100111111111110 U
0Z
b100 Y
1a
b11111111111111111111111111111111 ]
b0 g
b101 f
b100100100101101011101000111100101110000011001010010000001011000010011110101001001001001 i
b11111111111100101100001010010011 ;
b11111111111100101100001010010011 >
b11111111111100101100001010010011 R
b10 =
#3000
b10000 P
b10000 Q
b10 #
b10 A
01
b0 9
b0 E
b10010001101000101000000000000 *
b10010001101000101000000000000 C
b10010001101000101000000000000 X
0N
1H
b1000 "
b1000 @
b11 !
b11 ?
07
0:
14
b11 2
b11 D
10
b100100011 V
b100100101 T
b100100100100 W
b10010001101000101000000000000 S
b1000101100100100010 U
b10 d
b0 Y
b10010001101000101000000000000 ]
b0 f
b10011000101010101001001 i
b10010001101000101001010110111 ;
b10010001101000101001010110111 >
b10010001101000101001010110111 R
b1 <
#4000
b1 #
b1 A
1'
0H
1M
b1 d
1`
b100000101010101010010010101000001000011 i
b10010001101000101001010010111 ;
b10010001101000101001010010111 >
b10010001101000101001010010111 R
b10 <
#5000
b10 P
b10 Q
b1000 #
b1000 A
0'
15
b1000 *
b1000 C
b1000 X
1-
1I
0M
b110 "
b110 @
b1000 !
b1000 ?
13
04
b0 2
b0 D
00
1.
0/
b1000 V
b101 T
b100000000100 W
b100000110010000000000000 S
b110010000000001000 U
b1000 d
1e
0`
b1000 ]
b110 f
b100110001010111 i
b100000110010001010000011 ;
b100000110010001010000011 >
b100000110010001010000011 R
b11 <
#6000
b0 #
b0 A
b100 P
b100 Q
b1000 *
b1000 C
b1000 X
0-
0I
1,
1G
b1000 $
b1000 B
b101 !
b101 ?
b101 V
b1000 T
b1000 W
b10100110010000000000000 S
b110010100000000100 U
b0 d
1h
0e
b0 c
b101 g
b101001101010111 i
b10100110010010000100011 ;
b10100110010010000100011 >
b10100110010010000100011 R
b100 <
#7000
b1000 P
b1000 Q
0&
11
b1 2
b1 D
b10000 *
b10000 C
b10000 X
0,
0G
16
1L
b10000 $
b10000 B
b101 "
b101 @
b110 !
b110 ?
03
0.
b110 V
b10000 T
b10000 W
b11000101000000000000000 S
b101000000000000110 U
0h
1[
0a
b10000 ]
b110 g
b101 f
b10000100100010101010001 i
b11000101000100001100011 ;
b11000101000100001100011 >
b11000101000100001100011 R
b101 <
#8000
b100000 P
b100000 Q
b100 #
b100 A
1&
1)
1'
b10000 *
b10000 C
b10000 X
06
0L
1K
b101 $
b101 B
b0 "
b0 @
b10000 !
b10000 ?
b10000 V
b101 T
b100000000100 W
b1000000000000000000000000 S
b10000 U
b100 d
1^
0[
1a
1`
b101 c
b0 g
b0 f
b10010100100000101001100 i
b1000000000000001011101111 ;
b1000000000000001011101111 >
b1000000000000001011101111 R
b110 <
#9000
b10 P
b10 Q
0'
b1100 *
b1100 C
b1100 X
0K
1%
1J
b110 "
b110 @
b1100 !
b1100 ?
b1100 V
b110000110000000000000000 S
b110000000000001100 U
1b
0`
b1100 ]
b110 f
b1001010010000010100110001010010 i
b110000110000001011100111 ;
b110000110000001011100111 >
b110000110000001011100111 R
b111 <
#10000
b0 #
b0 A
b1 P
b1 Q
0)
b0 *
b0 C
b0 X
0%
0J
1F
b0 $
b0 B
b0 "
b0 @
b1 !
b1 ?
b1 V
b0 T
b0 W
b100000000000000000000 S
b100000000000 U
0b
b0 d
0^
b0 ]
b0 c
b0 f
1\
0_
b10001010100001001010010010001010100000101001011 i
1+
b100000000000001110011 ;
b100000000000001110011 >
b100000000000001110011 R
b1000 <
#11000
b1001 <
