submissions/phase_4/imm.v
// The immediate generator is responsible for decoding the 32-bit
// sign-extended immediate from the incoming instruction word. It is a purely
// combinational block that is expected to be embedded in the instruction
// decoder.
module imm (
    // Input instruction word. This is used to extract the relevant immediate
    // bits and assemble them into the final immediate.
    input  wire [31:0] i_inst,
    // Instruction format, determined by the instruction decoder based on the
    // opcode. This is one-hot encoded according to the following format:
    // [0] R-type
    // [1] I-type
    // [2] S-type
    // [3] B-type
    // [4] U-type
    // [5] J-type
    // Because the R-type format does not have an immediate, the output
    // immediate can be treated as a don't-care under this case.
    input  wire [ 5:0] i_format,
    // Output 32-bit immediate, sign-extended from the immediate bitstring.
    output reg  [31:0] o_immediate
);

    // Extract raw bit-fields according to RISC-V RV32I specification
    wire [31:0] imm_i = {{20{i_inst[31]}}, i_inst[31:20]};
    wire [31:0] imm_s = {{20{i_inst[31]}}, i_inst[31:25], i_inst[11:7]};
    wire [31:0] imm_b = {{20{i_inst[31]}}, i_inst[7], i_inst[30:25], i_inst[11:8], 1'b0};
    wire [31:0] imm_u = {i_inst[31:12], 12'b0};
    wire [31:0] imm_j = {{12{i_inst[31]}}, i_inst[19:12], i_inst[20], i_inst[30:21], 1'b0};

    // Combinational logic using case statement based on one-hot format encoding
    always @(*) begin
        case (i_format)
            6'b000010: o_immediate = imm_i; // I-type [1]
            6'b000100: o_immediate = imm_s; // S-type [2]
            6'b001000: o_immediate = imm_b; // B-type [3]
            6'b010000: o_immediate = imm_u; // U-type [4]
            6'b100000: o_immediate = imm_j; // J-type [5]
            default:   o_immediate = 32'b0; // R-type [0] or illegal format default
        endcase
    end

endmodule

testbenches/phase_2/no_trace/phase_2/imm_tb.v
`timescale 1ns / 1ps
`default_nettype none

module imm_tb;

    reg  [31:0] inst;
    reg  [5:0]  format;
    wire [31:0] immediate;

    integer passed;
    integer failed;

    imm dut (
        .i_inst      (inst),
        .i_format    (format),
        .o_immediate (immediate)
    );

    task check;
        input [511:0] label;
        input [31:0] t_inst;
        input [5:0]  t_format;
        input [31:0] expected;
        begin
            inst   = t_inst;
            format = t_format;
            #1;
            if (immediate === expected) begin
                passed = passed + 1;
                $display("[PASS] %0s", label);
            end else begin
                failed = failed + 1;
                $display("[FAIL] %0s", label);
                $display("       inst=%h format=%b immediate=%h expected=%h",
                         t_inst, t_format, immediate, expected);
            end
        end
    endtask

    initial begin
        $dumpfile("imm_tb.vcd");
        $dumpvars(0, imm_tb);

        passed = 0;
        failed = 0;

        $display("========== IMM testbench ==========");

        // I-type: addi x5,x6,8 and addi x5,x6,-1
        check("I-type positive", 32'h00830293, 6'b000010, 32'd8);
        check("I-type negative", 32'hfff30293, 6'b000010, 32'hffff_ffff);

        // S-type: sw x5,8(x6) and sw x5,-8(x6)
        check("S-type positive", 32'h00532423, 6'b000100, 32'd8);
        check("S-type negative", 32'hfe532c23, 6'b000100, 32'hffff_fff8);

        // B-type: beq x5,x6,+16 and beq x5,x6,-4
        check("B-type positive", 32'h00628863, 6'b001000, 32'd16);
        check("B-type negative", 32'hfe629ee3, 6'b001000, 32'hffff_fffc);

        // U-type: lui x5,0x12345
        check("U-type", 32'h123452b7, 6'b010000, 32'h1234_5000);

        // J-type: jal x5,+16 and jal x5,-4
        check("J-type positive", 32'h010002ef, 6'b100000, 32'd16);
        check("J-type negative", 32'hffdff2ef, 6'b100000, 32'hffff_fffc);

        // R-type / illegal format defaults to zero.
        check("R-type default", 32'h007302b3, 6'b000001, 32'd0);
        check("zero format default", 32'h00000000, 6'b000000, 32'd0);

        $display("===================================");
        $display("%0d passed, %0d failed", passed, failed);
        if (failed == 0) $display("ALL TESTS PASSED");
        else             $display("TEST FAILED");
        $finish;
    end

endmodule

`default_nettype wire

tests/phase_2/imm_tb.vcd
$date
	Thu Sep 10 16:44:32 2026
$end
$version
	Icarus Verilog
$end
$timescale
	1ps
$end
$scope module imm_tb $end
$var wire 32 ! immediate [31:0] $end
$var reg 6 " format [5:0] $end
$var reg 32 # inst [31:0] $end
$var integer 32 $ failed [31:0] $end
$var integer 32 % passed [31:0] $end
$scope module dut $end
$var wire 6 & i_format [5:0] $end
$var wire 32 ' i_inst [31:0] $end
$var wire 32 ( imm_u [31:0] $end
$var wire 32 ) imm_s [31:0] $end
$var wire 32 * imm_j [31:0] $end
$var wire 32 + imm_i [31:0] $end
$var wire 32 , imm_b [31:0] $end
$var reg 32 - o_immediate [31:0] $end
$upscope $end
$scope task check $end
$var reg 32 . expected [31:0] $end
$var reg 512 / label [511:0] $end
$var reg 6 0 t_format [5:0] $end
$var reg 32 1 t_inst [31:0] $end
$upscope $end
$upscope $end
$enddefinitions $end
$comment Show the parameter values. $end
$dumpall
$end
#0
$dumpvars
b100000110000001010010011 1
b10 0
b10010010010110101110100011110010111000001100101001000000111000001101111011100110110100101110100011010010111011001100101 /
b1000 .
b1000 -
b100000000100 ,
b1000 +
b110000000000001000 *
b101 )
b100000110000000000000000 (
b100000110000001010010011 '
b10 &
b0 %
b0 $
b100000110000001010010011 #
b10 "
b1000 !
$end
#1000
b11111111111111111111111111111111 !
b11111111111111111111111111111111 -
b11111111111111111111111111111111 +
b11111111111111111111111111100101 )
b11111111111111111111111111100100 ,
b11111111111100110000000000000000 (
b11111111111100110000111111111110 *
b11111111111100110000001010010011 #
b11111111111100110000001010010011 '
b11111111111111111111111111111111 .
b11111111111100110000001010010011 1
b10010010010110101110100011110010111000001100101001000000110111001100101011001110110000101110100011010010111011001100101 /
b1 %
#2000
b1000 !
b1000 -
b101 +
b1000 )
b1000 ,
b10100110010000000000000 (
b110010100000000100 *
b100 "
b100 &
b10100110010010000100011 #
b10100110010010000100011 '
b1000 .
b100 0
b10100110010010000100011 1
b10100110010110101110100011110010111000001100101001000000111000001101111011100110110100101110100011010010111011001100101 /
b10 %
#3000
b11111111111111111111111111111000 !
b11111111111111111111111111111000 -
b11111111111111111111111111100101 +
b11111111111111111111111111111000 )
b11111111111111111111011111111000 ,
b11111110010100110010000000000000 (
b11111111111100110010111111100100 *
b11111110010100110010110000100011 #
b11111110010100110010110000100011 '
b11111111111111111111111111111000 .
b11111110010100110010110000100011 1
b10100110010110101110100011110010111000001100101001000000110111001100101011001110110000101110100011010010111011001100101 /
b11 %
#4000
b10000 !
b10000 -
b110 +
b10000 )
b10000 ,
b11000101000000000000000 (
b101000000000000110 *
b1000 "
b1000 &
b11000101000100001100011 #
b11000101000100001100011 '
b10000 .
b1000 0
b11000101000100001100011 1
b10000100010110101110100011110010111000001100101001000000111000001101111011100110110100101110100011010010111011001100101 /
b100 %
#5000
b11111111111111111111111111111100 !
b11111111111111111111111111111100 -
b11111111111111111111111111100110 +
b11111111111111111111111111111101 )
b11111111111111111111111111111100 ,
b11111110011000101001000000000000 (
b11111111111100101001011111100110 *
b11111110011000101001111011100011 #
b11111110011000101001111011100011 '
b11111111111111111111111111111100 .
b11111110011000101001111011100011 1
b10000100010110101110100011110010111000001100101001000000110111001100101011001110110000101110100011010010111011001100101 /
b101 %
#6000
b10010001101000101000000000000 !
b10010001101000101000000000000 -
b100100011 +
b100100101 )
b100100100100 ,
b10010001101000101000000000000 (
b1000101100100100010 *
b10000 "
b10000 &
b10010001101000101001010110111 #
b10010001101000101001010110111 '
b10010001101000101000000000000 .
b10000 0
b10010001101000101001010110111 1
b10101010010110101110100011110010111000001100101 /
b110 %
#7000
b10000 !
b10000 -
b10000 +
b101 )
b100000000100 ,
b1000000000000000000000000 (
b10000 *
b100000 "
b100000 &
b1000000000000001011101111 #
b1000000000000001011101111 '
b10000 .
b100000 0
b1000000000000001011101111 1
b10010100010110101110100011110010111000001100101001000000111000001101111011100110110100101110100011010010111011001100101 /
b111 %
#8000
b11111111111111111111111111111100 !
b11111111111111111111111111111100 -
b11111111111111111111111111111101 +
b11111111111111111111111111100101 )
b11111111111111111111111111100100 ,
b11111111110111111111000000000000 (
b11111111111111111111111111111100 *
b11111111110111111111001011101111 #
b11111111110111111111001011101111 '
b11111111111111111111111111111100 .
b11111111110111111111001011101111 1
b10010100010110101110100011110010111000001100101001000000110111001100101011001110110000101110100011010010111011001100101 /
b1000 %
#9000
b0 !
b0 -
b111 +
b101 )
b100000000100 ,
b11100110000000000000000 (
b110000100000000110 *
b1 "
b1 &
b11100110000001010110011 #
b11100110000001010110011 '
b0 .
b1 0
b11100110000001010110011 1
b101001000101101011101000111100101110000011001010010000001100100011001010110011001100001011101010110110001110100 /
b1001 %
#10000
b0 +
b0 )
b0 ,
b0 (
b0 *
b0 "
b0 &
b0 #
b0 '
b0 0
b0 1
b1111010011001010111001001101111001000000110011001101111011100100110110101100001011101000010000001100100011001010110011001100001011101010110110001110100 /
b1010 %
#11000
b1011 %
