submissions/phase_3/rf_old.v
`default_nettype none

// The register file is effectively a single cycle memory with 32-bit words
// and depth 32. It has two asynchronous read ports, allowing two independent
// registers to be read at the same time combinationally, and one synchronous
// write port, allowing a register to be written to on the next clock edge.
//
// The register `x0` is hardwired to zero.
// NOTE: This can be implemented either by silently discarding writesto
// address 5'd0, or by muxing the output to zero when reading from that
// address.
module rf #(
    // When this parameter is set to 1, "RF bypass" mode is enabled. This
    // allows data at the write port to be observed at the read ports
    // immediately without having to wait for the next clock edge. This is
    // a common forwarding optimization in a pipelined core (phase 5), but will
    // cause a single-cycle processor to behave incorrectly. You are required
    // to implement and test both modes. In phase 4, you will disable this
    // parameter, before enabling it in phase 6.
    parameter BYPASS_EN = 0
) (
    // Global clock.
    input  wire        i_clk,
    // Synchronous active-high reset.
    input  wire        i_rst,
    // Both read register ports are asynchronous (zero-cycle). That is, read
    // data is visible combinationally without having to wait for a clock.
    //
    // The read ports are *independent* and can read two different registers
    // (but of course, also the same register if needed).
    //
    // Register `x0` is hardwired to zero, so reading from address 5'd0
    // should always return 32'd0 on either port regardless of any writes.
    //
    // Register read port 1, with input address [0, 31] and output data.
    input  wire [ 4:0] i_rs1_raddr,
    output wire [31:0] o_rs1_rdata,
    // Register read port 2, with input address [0, 31] and output data.
    input  wire [ 4:0] i_rs2_raddr,
    output wire [31:0] o_rs2_rdata,
    // The register write port is synchronous. When write is enabled, the
    // data at the write port will be written to the specified register
    // at the next clock edge. When the writen enable is low, the register
    // file should remain unchanged at the clock edge.
    //
    // Write register enable, address [0, 31] and input data.
    input  wire        i_rd_wen,
    input  wire [ 4:0] i_rd_waddr,
    input  wire [31:0] i_rd_wdata
);

    // Register storage: 32 registers of 32 bits each
    // x0 (registers[0]) is hardwired to zero via read muxing
    reg [31:0] registers [31:0];
    integer     i;
   

    // ========================================
    // Synchronous Write Port
    // ========================================
    always @(posedge i_clk) begin
        if (i_rst) begin
            // Reset all registers to zero
           registers[0] <= 32'b0;
           registers[1] <= 32'b0;
           registers[2] <= 32'b0;
           registers[3] <= 32'b0;
           registers[4] <= 32'b0;
           registers[5] <= 32'b0;
           registers[6] <= 32'b0;
           registers[7] <= 32'b0;
           registers[8] <= 32'b0;
           registers[9] <= 32'b0;
           registers[10] <= 32'b0;
           registers[11] <= 32'b0;
           registers[12] <= 32'b0;
           registers[13] <= 32'b0;
           registers[14] <= 32'b0;
           registers[15] <= 32'b0;
           registers[16] <= 32'b0;
           registers[17] <= 32'b0;
           registers[18] <= 32'b0;
           registers[19] <= 32'b0;
           registers[20] <= 32'b0;
           registers[21] <= 32'b0;
           registers[22] <= 32'b0;
           registers[23] <= 32'b0;
           registers[24] <= 32'b0;
           registers[25] <= 32'b0;
           registers[26] <= 32'b0;
           registers[27] <= 32'b0;
           registers[28] <= 32'b0;
           registers[29] <= 32'b0;
           registers[30] <= 32'b0;
           registers[31] <= 32'b0;
           
        end else if (i_rd_wen && i_rd_waddr != 5'b0) begin
            // Write to register file (except x0, which is read-only)
            // The condition i_rd_waddr != 5'b0 prevents writes to x0
            registers[i_rd_waddr] <= i_rd_wdata;
        end
    end

    // ========================================
    // Asynchronous Read Ports
    // ========================================
    wire [31:0] rs1_data = (i_rs1_raddr == 5'b0) ? 32'b0 : registers[i_rs1_raddr];
    wire [31:0] rs2_data = (i_rs2_raddr == 5'b0) ? 32'b0 : registers[i_rs2_raddr];

    // ========================================
    // Bypass Logic (Optional)
    // ========================================
    // In bypass mode, if a write is happening to the same register being read,
    // forward the write data immediately without waiting for the clock edge.
    // This is a common optimization in pipelined cores.
    generate
        if (BYPASS_EN) begin : bypass_mode
            // Read port 1: forward write data if address matches
            assign o_rs1_rdata = (i_rd_wen && i_rd_waddr == i_rs1_raddr && i_rd_waddr != 5'b0) 
                                 ? i_rd_wdata 
                                 : rs1_data;
            
            // Read port 2: forward write data if address matches
            assign o_rs2_rdata = (i_rd_wen && i_rd_waddr == i_rs2_raddr && i_rd_waddr != 5'b0) 
                                 ? i_rd_wdata 
                                 : rs2_data;
        end else begin : no_bypass_mode
            // Without bypass, reads see only what's in the register file
            assign o_rs1_rdata = rs1_data;
            assign o_rs2_rdata = rs2_data;
        end
    endgenerate

endmodule

`default_nettype wire

testbenches/phase_2/no_trace/phase_2/rf_tb.v
`timescale 1ns / 1ps
`default_nettype none

module rf_tb;

    reg         clk;
    reg         rst;
    reg  [4:0]  rs1_addr;
    reg  [4:0]  rs2_addr;
    reg         rd_wen;
    reg  [4:0]  rd_waddr;
    reg  [31:0] rd_wdata;

    wire [31:0] no_bp_rs1;
    wire [31:0] no_bp_rs2;
    wire [31:0] bp_rs1;
    wire [31:0] bp_rs2;

    integer passed;
    integer failed;

    rf #(.BYPASS_EN(0)) dut_no_bypass (
        .i_clk       (clk),
        .i_rst       (rst),
        .i_rs1_raddr (rs1_addr),
        .o_rs1_rdata (no_bp_rs1),
        .i_rs2_raddr (rs2_addr),
        .o_rs2_rdata (no_bp_rs2),
        .i_rd_wen    (rd_wen),
        .i_rd_waddr  (rd_waddr),
        .i_rd_wdata  (rd_wdata)
    );

    rf #(.BYPASS_EN(1)) dut_bypass (
        .i_clk       (clk),
        .i_rst       (rst),
        .i_rs1_raddr (rs1_addr),
        .o_rs1_rdata (bp_rs1),
        .i_rs2_raddr (rs2_addr),
        .o_rs2_rdata (bp_rs2),
        .i_rd_wen    (rd_wen),
        .i_rd_waddr  (rd_waddr),
        .i_rd_wdata  (rd_wdata)
    );

    task check_reads;
        input [511:0] label;
        input [31:0] expected1;
        input [31:0] expected2;
        begin
            #1;
            if (no_bp_rs1 === expected1 && no_bp_rs2 === expected2 &&
                bp_rs1    === expected1 && bp_rs2    === expected2) begin
                passed = passed + 1;
                $display("[PASS] %0s", label);
            end else begin
                failed = failed + 1;
                $display("[FAIL] %0s", label);
                $display("       no-bypass: rs1=%h rs2=%h", no_bp_rs1, no_bp_rs2);
                $display("       bypass:    rs1=%h rs2=%h", bp_rs1, bp_rs2);
                $display("       expected:  rs1=%h rs2=%h", expected1, expected2);
            end
        end
    endtask

    task clock_write;
        input [4:0] addr;
        input [31:0] data;
        begin
            rd_wen   = 1'b1;
            rd_waddr = addr;
            rd_wdata = data;
            #1;
            clk = 1'b1;
            #1;
            clk = 1'b0;
            #1;
            rd_wen = 1'b0;
        end
    endtask

    initial begin
        $dumpfile("rf_tb.vcd");
        $dumpvars(0, rf_tb);

        passed = 0;
        failed = 0;
        clk = 0;
        rst = 0;
        rs1_addr = 0;
        rs2_addr = 0;
        rd_wen = 0;
        rd_waddr = 0;
        rd_wdata = 0;

        $display("========== RF testbench ==========");

        // Synchronous reset.
        rst = 1'b1;
        #1;
        clk = 1'b1;
        #1;
        clk = 1'b0;
        #1;
        rst = 1'b0;

        rs1_addr = 0;
        rs2_addr = 0;
        check_reads("reset clears x0", 0, 0);

        // Normal writes and asynchronous reads.
        clock_write(5'd5, 32'h1234_5678);
        rs1_addr = 5'd5;
        rs2_addr = 5'd5;
        check_reads("write/read x5", 32'h1234_5678, 32'h1234_5678);

        // Independent read ports.
        clock_write(5'd6, 32'hdead_beef);
        rs1_addr = 5'd5;
        rs2_addr = 5'd6;
        check_reads("independent read ports", 32'h1234_5678, 32'hdead_beef);

        // x0 must remain zero even when a write is attempted.
        clock_write(5'd0, 32'hffff_ffff);
        rs1_addr = 0;
        rs2_addr = 5'd5;
        check_reads("x0 ignores writes", 0, 32'h1234_5678);

        // Write enable low must preserve the old value.
        rd_wen = 1'b0;
        rd_waddr = 5'd5;
        rd_wdata = 32'h0000_0000;
        #1;
        clk = 1'b1;
        #1;
        clk = 1'b0;
        #1;
        rs1_addr = 5'd5;
        rs2_addr = 5'd6;
        check_reads("write disabled preserves data", 32'h1234_5678, 32'hdead_beef);

        // Bypass mode: data must appear immediately before the clock edge.
        rs1_addr = 5'd5;
        rs2_addr = 5'd6;
        rd_wen = 1'b1;
        rd_waddr = 5'd5;
        rd_wdata = 32'haaaa_5555;
        #1;

        if (bp_rs1 === 32'haaaa_5555 &&
            no_bp_rs1 === 32'h1234_5678) begin
            passed = passed + 1;
            $display("[PASS] bypass forwards pending write");
        end else begin
            failed = failed + 1;
            $display("[FAIL] bypass forwards pending write");
            $display("       bypass=%h expected=%h", bp_rs1, 32'haaaa_5555);
            $display("       no-bypass=%h expected old=%h", no_bp_rs1, 32'h1234_5678);
        end

        // After the clock, both modes must contain the new value.
        clk = 1'b1;
        #1;
        clk = 1'b0;
        #1;
        rd_wen = 1'b0;
        check_reads("write commits to both modes", 32'haaaa_5555, 32'hdead_beef);

        // Bypass must not forward a write to x0.
        rs1_addr = 0;
        rd_wen = 1'b1;
        rd_waddr = 0;
        rd_wdata = 32'hcafebabe;
        #1;
        if (bp_rs1 === 0 && no_bp_rs1 === 0) begin
            passed = passed + 1;
            $display("[PASS] bypass does not forward x0");
        end else begin
            failed = failed + 1;
            $display("[FAIL] bypass does not forward x0");
        end

        $display("==================================");
        $display("%0d passed, %0d failed", passed, failed);
        if (failed == 0) $display("ALL TESTS PASSED");
        else             $display("TEST FAILED");
        $finish;
    end

endmodule

`default_nettype wire

tests/phase_2/rf_tb.vcd
$date
	Thu Sep 10 16:44:39 2026
$end
$version
	Icarus Verilog
$end
$timescale
	1ps
$end
$scope module rf_tb $end
$var wire 32 ! no_bp_rs2 [31:0] $end
$var wire 32 " no_bp_rs1 [31:0] $end
$var wire 32 # bp_rs2 [31:0] $end
$var wire 32 $ bp_rs1 [31:0] $end
$var reg 1 % clk $end
$var reg 5 & rd_waddr [4:0] $end
$var reg 32 ' rd_wdata [31:0] $end
$var reg 1 ( rd_wen $end
$var reg 5 ) rs1_addr [4:0] $end
$var reg 5 * rs2_addr [4:0] $end
$var reg 1 + rst $end
$var integer 32 , failed [31:0] $end
$var integer 32 - passed [31:0] $end
$scope module dut_bypass $end
$var wire 1 % i_clk $end
$var wire 5 . i_rd_waddr [4:0] $end
$var wire 32 / i_rd_wdata [31:0] $end
$var wire 1 ( i_rd_wen $end
$var wire 5 0 i_rs1_raddr [4:0] $end
$var wire 5 1 i_rs2_raddr [4:0] $end
$var wire 1 + i_rst $end
$var wire 32 2 rs2_data [31:0] $end
$var wire 32 3 rs1_data [31:0] $end
$var wire 32 4 o_rs2_rdata [31:0] $end
$var wire 32 5 o_rs1_rdata [31:0] $end
$var parameter 32 6 BYPASS_EN $end
$scope begin bypass_mode $end
$upscope $end
$upscope $end
$scope module dut_no_bypass $end
$var wire 1 % i_clk $end
$var wire 5 7 i_rd_waddr [4:0] $end
$var wire 32 8 i_rd_wdata [31:0] $end
$var wire 1 ( i_rd_wen $end
$var wire 5 9 i_rs1_raddr [4:0] $end
$var wire 5 : i_rs2_raddr [4:0] $end
$var wire 1 + i_rst $end
$var wire 32 ; rs2_data [31:0] $end
$var wire 32 < rs1_data [31:0] $end
$var wire 32 = o_rs2_rdata [31:0] $end
$var wire 32 > o_rs1_rdata [31:0] $end
$var parameter 32 ? BYPASS_EN $end
$scope begin no_bypass_mode $end
$upscope $end
$upscope $end
$scope task check_reads $end
$var reg 32 @ expected1 [31:0] $end
$var reg 32 A expected2 [31:0] $end
$var reg 512 B label [511:0] $end
$upscope $end
$scope task clock_write $end
$var reg 5 C addr [4:0] $end
$var reg 32 D data [31:0] $end
$upscope $end
$upscope $end
$enddefinitions $end
$comment Show the parameter values. $end
$dumpall
b0 ?
b1 6
$end
#0
$dumpvars
bx D
bx C
bx B
bx A
bx @
b0 >
b0 =
b0 <
b0 ;
b0 :
b0 9
b0 8
b0 7
b0 5
b0 4
b0 3
b0 2
b0 1
b0 0
b0 /
b0 .
b0 -
b0 ,
1+
b0 *
b0 )
0(
b0 '
b0 &
0%
b0 $
b0 #
b0 "
b0 !
$end
#1000
1%
#2000
0%
#3000
b0 A
b0 @
b11100100110010101110011011001010111010000100000011000110110110001100101011000010111001001110011001000000111100000110000 B
0+
#4000
b10010001101000101011001111000 '
b10010001101000101011001111000 /
b10010001101000101011001111000 8
b101 &
b101 .
b101 7
1(
b10010001101000101011001111000 D
b101 C
b1 -
#5000
1%
#6000
0%
#7000
b10010001101000101011001111000 #
b10010001101000101011001111000 4
b10010001101000101011001111000 $
b10010001101000101011001111000 5
b10010001101000101011001111000 2
b10010001101000101011001111000 !
b10010001101000101011001111000 =
b10010001101000101011001111000 ;
b10010001101000101011001111000 3
b10010001101000101011001111000 "
b10010001101000101011001111000 >
b10010001101000101011001111000 <
b10010001101000101011001111000 A
b10010001101000101011001111000 @
b1110111011100100110100101110100011001010010111101110010011001010110000101100100001000000111100000110101 B
b101 *
b101 1
b101 :
b101 )
b101 0
b101 9
0(
#8000
b11011110101011011011111011101111 '
b11011110101011011011111011101111 /
b11011110101011011011111011101111 8
b110 &
b110 .
b110 7
1(
b11011110101011011011111011101111 D
b110 C
b10 -
#9000
1%
#10000
0%
#11000
b11011110101011011011111011101111 #
b11011110101011011011111011101111 4
b11011110101011011011111011101111 2
b11011110101011011011111011101111 !
b11011110101011011011111011101111 =
b11011110101011011011111011101111 ;
b11011110101011011011111011101111 A
b1101001011011100110010001100101011100000110010101101110011001000110010101101110011101000010000001110010011001010110000101100100001000000111000001101111011100100111010001110011 B
b110 *
b110 1
b110 :
0(
#12000
b11111111111111111111111111111111 '
b11111111111111111111111111111111 /
b11111111111111111111111111111111 8
b0 &
b0 .
b0 7
1(
b11111111111111111111111111111111 D
b0 C
b11 -
#13000
1%
#14000
0%
#15000
b10010001101000101011001111000 #
b10010001101000101011001111000 4
b0 $
b0 5
b10010001101000101011001111000 2
b10010001101000101011001111000 !
b10010001101000101011001111000 =
b10010001101000101011001111000 ;
b0 3
b0 "
b0 >
b0 <
b10010001101000101011001111000 A
b0 @
b111100000110000001000000110100101100111011011100110111101110010011001010111001100100000011101110111001001101001011101000110010101110011 B
b101 *
b101 1
b101 :
b0 )
b0 0
b0 9
0(
#16000
b0 '
b0 /
b0 8
b101 &
b101 .
b101 7
b100 -
#17000
1%
#18000
0%
#19000
b11011110101011011011111011101111 #
b11011110101011011011111011101111 4
b10010001101000101011001111000 $
b10010001101000101011001111000 5
b11011110101011011011111011101111 2
b11011110101011011011111011101111 !
b11011110101011011011111011101111 =
b11011110101011011011111011101111 ;
b10010001101000101011001111000 3
b10010001101000101011001111000 "
b10010001101000101011001111000 >
b10010001101000101011001111000 <
b11011110101011011011111011101111 A
b10010001101000101011001111000 @
b111011101110010011010010111010001100101001000000110010001101001011100110110000101100010011011000110010101100100001000000111000001110010011001010111001101100101011100100111011001100101011100110010000001100100011000010111010001100001 B
b110 *
b110 1
b110 :
b101 )
b101 0
b101 9
#20000
b10101010101010100101010101010101 $
b10101010101010100101010101010101 5
b10101010101010100101010101010101 '
b10101010101010100101010101010101 /
b10101010101010100101010101010101 8
1(
b101 -
#21000
b10101010101010100101010101010101 3
b10101010101010100101010101010101 "
b10101010101010100101010101010101 >
b10101010101010100101010101010101 <
1%
b110 -
#22000
0%
#23000
b10101010101010100101010101010101 @
b11101110111001001101001011101000110010100100000011000110110111101101101011011010110100101110100011100110010000001110100011011110010000001100010011011110111010001101000001000000110110101101111011001000110010101110011 B
0(
#24000
b0 $
b0 5
b0 3
b0 "
b0 >
b0 <
b11001010111111101011101010111110 '
b11001010111111101011101010111110 /
b11001010111111101011101010111110 8
b0 &
b0 .
b0 7
1(
b0 )
b0 0
b0 9
b111 -
#25000
b1000 -
